DAY 003/mux_2_1.v
module mux_2_to_1 (
    input a, b, sel,
    output y
);
assign y = sel ? b:a;
endmodule

DAY 003/mux_tb.v
module mux_tb();
    reg a, b, sel;
    wire y;
    mux_2_to_1 MUX_UUT(
        .a(a), .b(b), .sel(sel), .y(y)
    );
    initial begin
        $dumpfile("mux_simulation.vcd");
        $dumpvars(0,mux_tb);
        $display("A B SEL | Y");
        a=0; b=0; sel=0; #10;
        $display("%b %b  %b | %b", a, b, sel, y);
        a=0; b=1; sel=0; #10;
        $display("%b %b  %b | %b", a, b, sel, y);
        a=1; b=0; sel=0; #10;
        $display("%b %b  %b | %b", a, b, sel, y);
        a=1; b=1; sel=0; #10;
        $display("%b %b  %b | %b", a, b, sel, y);
        a=0; b=0; sel=1; #10;
        $display("%b %b  %b | %b", a, b, sel, y);
        a=0; b=1; sel=1; #10;
        $display("%b %b  %b | %b", a, b, sel, y);
        a=1; b=0; sel=1; #10;
        $display("%b %b  %b | %b", a, b, sel, y);
        a=1; b=1; sel=1; #10;
        $display("%b %b  %b | %b", a, b, sel, y);
        $finish;
    end
endmodule

DAY 003/mux_simulation.vcd
$date
	Mon Jan 12 13:54:26 2026
$end
$version
	Icarus Verilog
$end
$timescale
	1s
$end
$scope module mux_tb $end
$var wire 1 ! y $end
$var reg 1 " a $end
$var reg 1 # b $end
$var reg 1 $ sel $end
$scope module MUX_UUT $end
$var wire 1 " a $end
$var wire 1 # b $end
$var wire 1 $ sel $end
$var wire 1 ! y $end
$upscope $end
$upscope $end
$enddefinitions $end
$comment Show the parameter values. $end
$dumpall
$end
#0
$dumpvars
0$
0#
0"
0!
$end
#10
1#
#20
1!
0#
1"
#30
1#
#40
0!
1$
0#
0"
#50
1!
1#
#60
0!
0#
1"
#70
1!
1#
