DAY 002/full_adder.v
// Dataflow modeling of full adder
module full_adder (
  input a, b, cin,
  output sum, carry
);

  assign sum  = a ^ b ^ cin;
  assign carry = (a & b) | (b & cin) | (cin & a);

endmodule

DAY 002/4bit_rca.v
// Dataflow modeling of 4-bit ripple carry adder
module ripple_carry_adder_4bit (
    input [3:0] A, B,
    input cin,
    output [3:0] sum,
    output cout
    );
    
    wire c1, c2, c3;
    
    full_adder FA0 (
        .a(A[0]),
        .b(B[0]),
        .cin(cin),
        .sum(sum[0]),
        .carry(c1)
    );
    
    full_adder FA1 (
        .a(A[1]),
        .b(B[1]),
        .cin(c1),
        .sum(sum[1]),
        .carry(c2)
    );
    
    full_adder FA2 (
        .a(A[2]),
        .b(B[2]),
        .cin(c2),
        .sum(sum[2]),
        .carry(c3)
    );
    
    full_adder FA3 (
        .a(A[3]),
        .b(B[3]),
        .cin(c3),
        .sum(sum[3]),
        .carry(cout)
    );

endmodule

DAY 002/half_adder.v
// Dataflow modeling of half adder
module half_adder (
  input a, b,
  output sum, carry
);

  assign sum  = a ^ b;
  assign carry = a & b;

endmodule

DAY 002/adder_tb.v
`timescale 1ns / 1ps

module master_tb;

    // --- 1. Variables for Half Adder & Full Adder Testing ---
    reg a, b, cin;
    wire ha_sum, ha_carry;
    wire fa_sum, fa_carry;

    // --- 2. Variables for 4-bit RCA Testing ---
    reg [3:0] A_bus, B_bus;
    reg cin_rca;
    wire [3:0] sum_rca;
    wire cout_rca;

    // --- INSTANTIATION: Connecting your separate files ---
    
    // Unit 1: The Half Adder
    half_adder HA_UUT (
        .a(a), .b(b), 
        .sum(ha_sum), .carry(ha_carry)
    );

    // Unit 2: The Full Adder
    full_adder FA_UUT (
        .a(a), .b(b), .cin(cin), 
        .sum(fa_sum), .carry(fa_carry)
    );

    // Unit 3: The 4-bit Ripple Carry Adder
    ripple_carry_adder_4bit RCA_UUT (
        .A(A_bus), .B(B_bus), .cin(cin_rca), 
        .sum(sum_rca), .cout(cout_rca)
    );

    // --- TEST SEQUENCE ---
    initial begin
        $dumpfile("master_simulation.vcd");
        $dumpvars(0, master_tb);

        // ==========================================
        // TEST 1: Half Adder
        // ==========================================
        $display("-----------------------------------------");
        $display("Testing Half Adder (half_adder.v)");
        $display("A B | Sum Carry");
        
        a=0; b=0; #10; $display("%b %b |  %b    %b", a, b, ha_sum, ha_carry);
        a=0; b=1; #10; $display("%b %b |  %b    %b", a, b, ha_sum, ha_carry);
        a=1; b=0; #10; $display("%b %b |  %b    %b", a, b, ha_sum, ha_carry);
        a=1; b=1; #10; $display("%b %b |  %b    %b", a, b, ha_sum, ha_carry);

        // ==========================================
        // TEST 2: Full Adder
        // ==========================================
        $display("\n-----------------------------------------");
        $display("Testing Full Adder (full_adder.v)");
        $display("A B Cin | Sum Carry");

        a=0; b=0; cin=0; #10; $display("%b %b  %b  |  %b    %b", a, b, cin, fa_sum, fa_carry);
        a=0; b=1; cin=0; #10; $display("%b %b  %b  |  %b    %b", a, b, cin, fa_sum, fa_carry);
        a=1; b=1; cin=0; #10; $display("%b %b  %b  |  %b    %b", a, b, cin, fa_sum, fa_carry);
        a=1; b=1; cin=1; #10; $display("%b %b  %b  |  %b    %b", a, b, cin, fa_sum, fa_carry);

        // ==========================================
        // TEST 3: 4-bit Ripple Carry Adder
        // ==========================================
        $display("\n-----------------------------------------");
        $display("Testing 4-bit RCA (4bit_rca.v)");
        $display("  A     B   Cin |  Sum   Cout");

        // 2 + 3 = 5
        A_bus=4'd2; B_bus=4'd3; cin_rca=0; #10;
        $display("%b  %b   %b  | %b    %b (Expect 0101)", A_bus, B_bus, cin_rca, sum_rca, cout_rca);

        // 15 + 1 = 0 (with Carry out)
        A_bus=4'd15; B_bus=4'd1; cin_rca=0; #10;
        $display("%b  %b   %b  | %b    %b (Expect 0000, Cout=1)", A_bus, B_bus, cin_rca, sum_rca, cout_rca);

        // 10 + 5 + 1 (cin) = 0 (with Carry out)
        A_bus=4'd10; B_bus=4'd5; cin_rca=1; #10;
        $display("%b  %b   %b  | %b    %b (Expect 0000, Cout=1)", A_bus, B_bus, cin_rca, sum_rca, cout_rca);

        $finish;
    end

endmodule

DAY 002/master_simulation.vcd
$date
	Sun Jan 11 18:49:02 2026
$end
$version
	Icarus Verilog
$end
$timescale
	1ps
$end
$scope module master_tb $end
$var wire 4 ! sum_rca [3:0] $end
$var wire 1 " ha_sum $end
$var wire 1 # ha_carry $end
$var wire 1 $ fa_sum $end
$var wire 1 % fa_carry $end
$var wire 1 & cout_rca $end
$var reg 4 ' A_bus [3:0] $end
$var reg 4 ( B_bus [3:0] $end
$var reg 1 ) a $end
$var reg 1 * b $end
$var reg 1 + cin $end
$var reg 1 , cin_rca $end
$scope module FA_UUT $end
$var wire 1 ) a $end
$var wire 1 * b $end
$var wire 1 % carry $end
$var wire 1 + cin $end
$var wire 1 $ sum $end
$upscope $end
$scope module HA_UUT $end
$var wire 1 ) a $end
$var wire 1 * b $end
$var wire 1 # carry $end
$var wire 1 " sum $end
$upscope $end
$scope module RCA_UUT $end
$var wire 4 - A [3:0] $end
$var wire 4 . B [3:0] $end
$var wire 1 , cin $end
$var wire 4 / sum [3:0] $end
$var wire 1 & cout $end
$var wire 1 0 c3 $end
$var wire 1 1 c2 $end
$var wire 1 2 c1 $end
$scope module FA0 $end
$var wire 1 3 a $end
$var wire 1 4 b $end
$var wire 1 2 carry $end
$var wire 1 , cin $end
$var wire 1 5 sum $end
$upscope $end
$scope module FA1 $end
$var wire 1 6 a $end
$var wire 1 7 b $end
$var wire 1 1 carry $end
$var wire 1 2 cin $end
$var wire 1 8 sum $end
$upscope $end
$scope module FA2 $end
$var wire 1 9 a $end
$var wire 1 : b $end
$var wire 1 0 carry $end
$var wire 1 1 cin $end
$var wire 1 ; sum $end
$upscope $end
$scope module FA3 $end
$var wire 1 < a $end
$var wire 1 = b $end
$var wire 1 & carry $end
$var wire 1 0 cin $end
$var wire 1 > sum $end
$upscope $end
$upscope $end
$upscope $end
$enddefinitions $end
$comment Show the parameter values. $end
$dumpall
$end
#0
$dumpvars
x>
x=
x<
x;
x:
x9
x8
x7
x6
x5
x4
x3
x2
x1
x0
bx /
bx .
bx -
x,
x+
0*
0)
bx (
bx '
x&
0%
x$
0#
0"
bx !
$end
#10000
x%
1"
1*
#20000
0*
1)
#30000
1%
0"
1#
1*
#40000
0%
0$
0#
0+
0*
0)
#50000
1$
1"
1*
#60000
1%
0$
0"
1#
1)
#70000
1$
1+
#80000
1;
0>
08
11
00
0&
02
b101 !
b101 /
15
14
17
0:
0=
03
16
09
0<
0,
b11 (
b11 .
b10 '
b10 -
#90000
1&
11
12
08
05
0;
10
b0 !
b0 /
0>
07
13
19
1<
b1 (
b1 .
b1111 '
b1111 -
#100000
1&
0>
10
b0 !
b0 /
05
1:
03
09
1,
b101 (
b101 .
b1010 '
b1010 -
